{
  "id": "task.obs.scaffold_logging_integration.v1",
  "kind": "atom",
  "version": 1,
  "meta": { "visibility": "internal", "priority": 6 },
  "title": "Observability: Scaffold logging integration",
  "description": "Adds structured logging hooks following the schema and correlation contract, without selecting a specific logging library by name.",
  "tags": ["observability", "logging", "scaffold"],
  "updatedUtc": "2025-12-28T00:00:00Z",
  "content": {
    "action": "obs_scaffold_logging_integration",
    "inputs": ["projectRoot", "logSchema", "correlationContract", "redactionPolicy"],
    "outputs": ["changedFiles", "loggingEntryPoints"],
    "rules": [
      "do not change public behavior except adding logs",
      "ensure logs are structured and consistent",
      "apply redaction everywhere logs are emitted"
    ]
  }
}
